krun/__init__.py
krun-0.1.0.dist-info/LICENSE
krun-0.1.0.dist-info/WHEEL
krun-0.1.0.dist-info/METADATA
krun-0.1.0.dist-info/RECORD
